wcdl/__init__.py
wcdl/download.py
wcdl/fetch.py
wcdl/main.py
wcdl/settings.py
wcdl/tools.py
wcdl-0.1.2.dist-info/METADATA
wcdl-0.1.2.dist-info/WHEEL
wcdl-0.1.2.dist-info/entry_points.txt
wcdl-0.1.2.dist-info/licenses/LICENSE
wcdl-0.1.2.dist-info/RECORD
