Metadata-Version: 2.4
Name: wcdl
Version: 0.1.2
Summary: 
License-File: LICENSE
Author: rebin
Author-email: rebinmahmoudi14@gmail.com
Requires-Python: >=3.13
Classifier: Programming Language :: Python :: 3
Classifier: Programming Language :: Python :: 3.13
Classifier: Programming Language :: Python :: 3.14
Requires-Dist: beautifulsoup4 (>=4.14.3,<5.0.0)
Requires-Dist: click (>=8.3.1,<9.0.0)
Requires-Dist: requests (>=2.32.5,<3.0.0)
Requires-Dist: rich (>=14.2.0,<15.0.0)
